{
  "+0zv6g": {
    "defaultMessage": "Image"
  },
  "+AcVD+": {
    "defaultMessage": "No emails, just awesomeness!"
  },
  "+sdKx8": {
    "defaultMessage": "Live now"
  },
  "+vVZ/G": {
    "defaultMessage": "Connect"
  },
  "+y6JUK": {
    "defaultMessage": "Raids"
  },
  "/0TOL5": {
    "defaultMessage": "Amount"
  },
  "/563b0": {
    "defaultMessage": "Balance: {n} sats"
  },
  "/EvlqN": {
    "defaultMessage": "nostr signer extension"
  },
  "/JkXBo": {
    "defaultMessage": "Clip from {title}"
  },
  "/Jp9pC": {
    "defaultMessage": "Total: {amount} sats"
  },
  "/aFYQ5": {
    "defaultMessage": "Stream Forwarding (optional)"
  },
  "/w4RM6": {
    "defaultMessage": "IRL"
  },
  "01iNut": {
    "defaultMessage": "Nostr address does not belong to you"
  },
  "04lmFi": {
    "defaultMessage": "Save Key"
  },
  "0VV/sK": {
    "defaultMessage": "Goal"
  },
  "0hNxBy": {
    "defaultMessage": "Starts"
  },
  "0rVLjV": {
    "defaultMessage": "No streams yet"
  },
  "1EYCdR": {
    "defaultMessage": "Tags"
  },
  "1LBny5": {
    "defaultMessage": "Stopped"
  },
  "1q4BO/": {
    "defaultMessage": "Not a valid URL"
  },
  "1qsXCO": {
    "defaultMessage": "eg. name@wallet.com"
  },
  "2/2yg+": {
    "defaultMessage": "Add"
  },
  "2lVQYF": {
    "defaultMessage": "...more"
  },
  "2ukA4d": {
    "defaultMessage": "{n} hours"
  },
  "2wdFaB": {
    "defaultMessage": "End Stream"
  },
  "37mth/": {
    "defaultMessage": "Viewers"
  },
  "3HwrQo": {
    "defaultMessage": "Zap!"
  },
  "3adEeb": {
    "defaultMessage": "{n} viewers"
  },
  "3df560": {
    "defaultMessage": "Login with private key"
  },
  "3kbIhS": {
    "defaultMessage": "Untitled"
  },
  "3yk8fB": {
    "defaultMessage": "Wallet"
  },
  "47FYwb": {
    "defaultMessage": "Cancel"
  },
  "4RhY4O": {
    "defaultMessage": "Example settings in OBS (Apple M1 Mac)"
  },
  "4XfMux": {
    "defaultMessage": "Videos"
  },
  "4iBdw1": {
    "defaultMessage": "Raid"
  },
  "4l69eO": {
    "defaultMessage": "Hmm, your lightning address looks wrong"
  },
  "4l6vz1": {
    "defaultMessage": "Copy"
  },
  "50+/JW": {
    "defaultMessage": "Stream Key is required"
  },
  "58DXVG": {
    "defaultMessage": "To get started, grab your stream key from the platform you wish to forward to."
  },
  "5JcXdV": {
    "defaultMessage": "Create Account"
  },
  "5L4ati": {
    "defaultMessage": "Zap from"
  },
  "5LXWMX": {
    "defaultMessage": "New Goal"
  },
  "5QYdPU": {
    "defaultMessage": "Start Time"
  },
  "5Wwopw": {
    "defaultMessage": "Pricing"
  },
  "5kx+2v": {
    "defaultMessage": "Server Url"
  },
  "5tM0VD": {
    "defaultMessage": "Stream Started"
  },
  "5vMmmR": {
    "defaultMessage": "Usernames are not unique on Nostr. The nostr address is your unique human-readable address that is unique to you upon registration."
  },
  "69hmpj": {
    "defaultMessage": "Raid from {name}"
  },
  "6PK5Jy": {
    "defaultMessage": "Past Stream"
  },
  "6Z2pvJ": {
    "defaultMessage": "Stream Providers"
  },
  "6pr6hJ": {
    "defaultMessage": "Minimum amount for text to speech"
  },
  "7+bCC1": {
    "defaultMessage": "Stream url must start with rtmp://"
  },
  "74PejI": {
    "defaultMessage": "Top Viewers"
  },
  "79lLl+": {
    "defaultMessage": "Music"
  },
  "7UOvbT": {
    "defaultMessage": "Offline"
  },
  "89UZph": {
    "defaultMessage": "Configure your streaming software"
  },
  "8YT6ja": {
    "defaultMessage": "Insert text to speak"
  },
  "8aAwpp": {
    "defaultMessage": "For manual hosting all you need is the HLS URL for the Stream URL field. You should be ale to find this in your hosting setup."
  },
  "8xVdjn": {
    "defaultMessage": "Video Codec"
  },
  "9WRlF4": {
    "defaultMessage": "Send"
  },
  "9ZoFpI": {
    "defaultMessage": "Delete file"
  },
  "9a9+ww": {
    "defaultMessage": "Title"
  },
  "9pMqYs": {
    "defaultMessage": "Nostr Address"
  },
  "9rmSgv": {
    "defaultMessage": "OBS (Open Broadcaster Software) is a free and open source software for video recording and live streaming on Windows, Mac and Linux. It is a popular choice with streamers. You'll need to install this to capture your video, audio and anything else you'd like to add to your stream. Once installed and configured to preference, add your Stream URL and Stream Key from the Stream settings to OBS to form a connection with zap.stream."
  },
  "A1zT+z": {
    "defaultMessage": "Search results: {term}"
  },
  "A7K3S+": {
    "defaultMessage": "Account Setup"
  },
  "ALdW69": {
    "defaultMessage": "Note by {name}"
  },
  "ASKb16": {
    "defaultMessage": "A description of the stream"
  },
  "AYIR/J": {
    "defaultMessage": "Remove Image"
  },
  "Atr2p4": {
    "defaultMessage": "NSFW Content"
  },
  "AukrPM": {
    "defaultMessage": "No viewer data available"
  },
  "Axo/o5": {
    "defaultMessage": "Science & Technology"
  },
  "AyGauy": {
    "defaultMessage": "Login"
  },
  "BD0vyn": {
    "defaultMessage": "{name} created a clip"
  },
  "Bd1yEX": {
    "defaultMessage": "New Stream Goal"
  },
  "Bep/gA": {
    "defaultMessage": "Private key"
  },
  "BzQPM+": {
    "defaultMessage": "Destination"
  },
  "C81/uG": {
    "defaultMessage": "Logout"
  },
  "CTgA2G": {
    "defaultMessage": "Create a new account if you don't have one already."
  },
  "CsCUYo": {
    "defaultMessage": "{n} sats"
  },
  "CsS/fy": {
    "defaultMessage": "{estimate} remaining ({balance} sats @ {rate} sats / {unit})"
  },
  "D3idYv": {
    "defaultMessage": "Settings"
  },
  "DZKuuP": {
    "defaultMessage": "Logged in as"
  },
  "DkgCAz": {
    "defaultMessage": "How do i stream on zap.stream?"
  },
  "Dn82AL": {
    "defaultMessage": "Live"
  },
  "DqmiAe": {
    "defaultMessage": "Dont have a nostr extension? Try {nos2x}, {nostore} or {alby}"
  },
  "E7n6zr": {
    "defaultMessage": "Current stream cost: {amount} sats/{unit} (about {usd}/day for a {x}hr stream)"
  },
  "E9APoR": {
    "defaultMessage": "Could not create stream URL"
  },
  "ESyhzp": {
    "defaultMessage": "Your comment for {name}"
  },
  "EcglP9": {
    "defaultMessage": "Key"
  },
  "FAUhZf": {
    "defaultMessage": "What are sats?"
  },
  "FIDK5Y": {
    "defaultMessage": "All Time Top Zappers"
  },
  "FXepR9": {
    "defaultMessage": "{m}mo {ago}",
    "description": "Number of month(s) relative to now"
  },
  "FjDlus": {
    "defaultMessage": "You can always replace it with your own address later."
  },
  "Fodi9+": {
    "defaultMessage": "Get paid by viewers"
  },
  "G/yZLu": {
    "defaultMessage": "Remove"
  },
  "G857ni": {
    "defaultMessage": "LNURL or invoice"
  },
  "GGaJMU": {
    "defaultMessage": "Top Chatters"
  },
  "GSuQPh": {
    "defaultMessage": "Unknown event link"
  },
  "GSye7T": {
    "defaultMessage": "Lightning Address"
  },
  "GcozGF": {
    "defaultMessage": "Invalid lightning address"
  },
  "Gq6x9o": {
    "defaultMessage": "Cover Image"
  },
  "Gvxoji": {
    "defaultMessage": "Name is required"
  },
  "GwbTAz": {
    "defaultMessage": "Streams"
  },
  "H/bNs9": {
    "defaultMessage": "Save this and keep it safe! If you lose this key, you won't be able to access your account ever again. Yep, it's that serious!"
  },
  "H1fdc9": {
    "defaultMessage": "Please add a thumbnail"
  },
  "H4hJvF": {
    "defaultMessage": "Choose a category"
  },
  "H5+NAX": {
    "defaultMessage": "Balance"
  },
  "HAlOn1": {
    "defaultMessage": "Name"
  },
  "HDgXO/": {
    "defaultMessage": "zap.stream is an open source platform powered by the nostr protocol. There are no giant corporations or giant funds available to provide free streaming."
  },
  "HsgeUk": {
    "defaultMessage": "Come check out my stream on zap.stream! {link}"
  },
  "Ht231k": {
    "defaultMessage": "Forwarding"
  },
  "HvUhXt": {
    "defaultMessage": "Uploading to {n} servers"
  },
  "I1kjHI": {
    "defaultMessage": "Supports {markdown}"
  },
  "I2AKfn": {
    "defaultMessage": "Gaming"
  },
  "IDqXmC": {
    "defaultMessage": "Media Server List"
  },
  "IJDKz3": {
    "defaultMessage": "Zap amount in {currency}"
  },
  "INlWvJ": {
    "defaultMessage": "OR"
  },
  "IPXhUW": {
    "defaultMessage": "Last Stream Summary"
  },
  "IqcyS0": {
    "defaultMessage": "What is a nostr extension?"
  },
  "J/+m9y": {
    "defaultMessage": "Stream Duration {duration} mins"
  },
  "JCIgkj": {
    "defaultMessage": "Username"
  },
  "JO0kq9": {
    "defaultMessage": "Edit Stream Info"
  },
  "JkLHGw": {
    "defaultMessage": "Website"
  },
  "Jq3FDz": {
    "defaultMessage": "Content"
  },
  "K3r6DQ": {
    "defaultMessage": "Delete"
  },
  "K7AkdL": {
    "defaultMessage": "Show"
  },
  "KH2ayq": {
    "defaultMessage": "Upload Video"
  },
  "KkIL3s": {
    "defaultMessage": "No, I am under 18"
  },
  "KtrGU6": {
    "defaultMessage": "If you already have an account, you can use a nostr extension to log in. If you already use a nostr extension, you will be automatically logged in. If you don't have a nostr extension set up, you can use nos2x or Alby."
  },
  "KxfKnW": {
    "defaultMessage": "Withdraw funds"
  },
  "LEmxc8": {
    "defaultMessage": "Zap Goals"
  },
  "LUvSJB": {
    "defaultMessage": "zap.stream is free up to 2 hours of hosting at high quality and up to 8 hours of “source” quality. After that you have an option to stream for 5 sats per minute or 10 sats per minute depending on your chosen quality. If you do not use zap.stream to host, pricing will depend on your chosen streaming provider."
  },
  "Le+99Z": {
    "defaultMessage": "Streamers pay a small fee to cover our running costs. We give new streamers a credit of {amount} sats (about {time_estimate} of streaming) to get started!"
  },
  "Lg2ye2": {
    "defaultMessage": "ZapStream is a new kind of streaming platform that allows you to earn bitcoin (sats) the moment you start streaming! Viewers can tip streamers any amount they choose. The tips are instantly deposited to your bitcoin (lightning) wallet. zap.stream never touches your earnings!"
  },
  "LknBsU": {
    "defaultMessage": "Stream Key"
  },
  "LxSJOb": {
    "defaultMessage": "Go to Dashboard"
  },
  "MTHO1W": {
    "defaultMessage": "Start Raid"
  },
  "My6HwN": {
    "defaultMessage": "Ok, it's safe"
  },
  "NTpJIm": {
    "defaultMessage": "Enable Recording"
  },
  "NnHu0L": {
    "defaultMessage": "Please upload at least 1 video"
  },
  "Ntjkqd": {
    "defaultMessage": "or"
  },
  "O2Cy6m": {
    "defaultMessage": "Yes, I am over 18"
  },
  "O7AeYh": {
    "defaultMessage": "Description.."
  },
  "OEW7yJ": {
    "defaultMessage": "Zaps"
  },
  "OKhRC6": {
    "defaultMessage": "Share"
  },
  "ORGv1Q": {
    "defaultMessage": "Created"
  },
  "OadZli": {
    "defaultMessage": "Manage Servers"
  },
  "ObZZEz": {
    "defaultMessage": "No clips yet"
  },
  "OkXMLE": {
    "defaultMessage": "Max Audio Bitrate"
  },
  "OumUwz": {
    "defaultMessage": "{m}s {ago}",
    "description": "Number of second(s) relative to now"
  },
  "Oxqtyf": {
    "defaultMessage": "We hooked you up with a lightning wallet so you can get paid by viewers right away!"
  },
  "PDA8V2": {
    "defaultMessage": "{m}h {ago}",
    "description": "Number of hour(s) relative to now"
  },
  "PHE60k": {
    "defaultMessage": "Leave blank if you do not wish to set up any goals."
  },
  "PUymyQ": {
    "defaultMessage": "Come check out {name} stream on zap.stream! {link}"
  },
  "PXAur5": {
    "defaultMessage": "Withdraw"
  },
  "Pc+tM3": {
    "defaultMessage": "Generate"
  },
  "Pe0ogR": {
    "defaultMessage": "Theme"
  },
  "PySFxG": {
    "defaultMessage": "Choose file."
  },
  "Q3au2v": {
    "defaultMessage": "About {estimate}"
  },
  "Q8Qw5B": {
    "defaultMessage": "Description"
  },
  "QNvtaq": {
    "defaultMessage": "Share on X"
  },
  "QRHNuF": {
    "defaultMessage": "What are we steaming today?"
  },
  "QRRCp0": {
    "defaultMessage": "Stream URL"
  },
  "QWlMq9": {
    "defaultMessage": "Stream key"
  },
  "QceMQZ": {
    "defaultMessage": "Goal: {amount}"
  },
  "Qe1MJu": {
    "defaultMessage": "{name} with {amount}"
  },
  "Qf0ugr": {
    "defaultMessage": "Here you have a few options, using our in-house hosting, or your own (such as Cloudflare)."
  },
  "R72je0": {
    "defaultMessage": "Stream Title"
  },
  "RGYBjE": {
    "defaultMessage": "Thumbnail"
  },
  "RJOmzk": {
    "defaultMessage": "I have read and agree with {provider}''s {terms}."
  },
  "RS6smY": {
    "defaultMessage": "Raid Message"
  },
  "RXQdxR": {
    "defaultMessage": "Please login to write messages!"
  },
  "RrCui3": {
    "defaultMessage": "Summary"
  },
  "RtYNX5": {
    "defaultMessage": "Chat Users"
  },
  "S39ba6": {
    "defaultMessage": "What is OBS?"
  },
  "SC2nJT": {
    "defaultMessage": "Audio Codec"
  },
  "Sjo1P4": {
    "defaultMessage": "Custom"
  },
  "TDUfVk": {
    "defaultMessage": "Started"
  },
  "TP/cMX": {
    "defaultMessage": "Ended"
  },
  "TcDwEB": {
    "defaultMessage": "Stream Keys"
  },
  "TwyMau": {
    "defaultMessage": "Account"
  },
  "UCDS65": {
    "defaultMessage": "ago",
    "description": "Relative time, ie. 1s ago"
  },
  "UGFYV8": {
    "defaultMessage": "Welcome to zap.stream!"
  },
  "UJBFYK": {
    "defaultMessage": "Add Card"
  },
  "UfSot5": {
    "defaultMessage": "Past Streams"
  },
  "Uo/DWG": {
    "defaultMessage": "About too long"
  },
  "VA/Z1S": {
    "defaultMessage": "Hide"
  },
  "VDOpia": {
    "defaultMessage": "What are zaps?"
  },
  "VKb1MS": {
    "defaultMessage": "Categories"
  },
  "W7DNWx": {
    "defaultMessage": "Stream Forwarding"
  },
  "W7IRLs": {
    "defaultMessage": "Your title is too short"
  },
  "W9355R": {
    "defaultMessage": "Unmute"
  },
  "WVJZ0U": {
    "defaultMessage": "Value",
    "description": "Config value column header"
  },
  "WcZM+B": {
    "defaultMessage": "File List"
  },
  "Wp4l7+": {
    "defaultMessage": "More Videos"
  },
  "WsjXrZ": {
    "defaultMessage": "Click on Log In"
  },
  "X2PZ7D": {
    "defaultMessage": "Create Goal"
  },
  "XIvYvF": {
    "defaultMessage": "Failed to get invoice"
  },
  "XMGfiA": {
    "defaultMessage": "Recent Clips"
  },
  "XgWvGA": {
    "defaultMessage": "Reactions"
  },
  "XmQZr5": {
    "defaultMessage": "No keys"
  },
  "Xq2sb0": {
    "defaultMessage": "To go live, copy and paste your Server URL and Stream Key below into your streaming software settings and press 'Start Streaming'. We recommend <a>OBS</a>."
  },
  "Y0DXJb": {
    "defaultMessage": "Recording URL"
  },
  "YPh5Nq": {
    "defaultMessage": "@ {rate}",
    "description": "Showing zap amount in USD @ rate"
  },
  "YjhNaf": {
    "defaultMessage": "Create Stream"
  },
  "YwzT/0": {
    "defaultMessage": "Clip title"
  },
  "YyXVHf": {
    "defaultMessage": "Clear Draft"
  },
  "Z8ZOEY": {
    "defaultMessage": "This method is insecure. We recommend using a {nostrlink}"
  },
  "ZXp0z1": {
    "defaultMessage": "Features"
  },
  "ZaNcK4": {
    "defaultMessage": "No goals yet"
  },
  "ZcgtZo": {
    "defaultMessage": "We've put together a list of easy-to-use exchanges that will allow you to buy a small amount of bitcoin (sats) and to transfer them to your wallet of choice."
  },
  "ZmqxZs": {
    "defaultMessage": "You can change this later"
  },
  "ZsYhvh": {
    "defaultMessage": "Zaps are lightning payments, which are published on nostr as receipts."
  },
  "Zse7yG": {
    "defaultMessage": "Raid target"
  },
  "aB/rH0": {
    "defaultMessage": "{m}h {ago}",
    "description": "Number of minute(s) relative to now"
  },
  "acrOoz": {
    "defaultMessage": "Continue"
  },
  "aqjZxs": {
    "defaultMessage": "Raid!"
  },
  "bD/ZwY": {
    "defaultMessage": "Edit Cards"
  },
  "bbUGS7": {
    "defaultMessage": "Recommended Stream Settings"
  },
  "bdH+0f": {
    "defaultMessage": "Balance History"
  },
  "bfvyfs": {
    "defaultMessage": "Anon"
  },
  "c3LlRO": {
    "defaultMessage": "{n}KiB"
  },
  "cPIKU2": {
    "defaultMessage": "Following"
  },
  "ccXLVi": {
    "defaultMessage": "Category"
  },
  "cg1VJ2": {
    "defaultMessage": "Connect Wallet"
  },
  "cntHHJ": {
    "defaultMessage": "This allows you to forward your stream to other platforms to reach a wider audience."
  },
  "cvAsEh": {
    "defaultMessage": "Streamed on {date}"
  },
  "cyR7Kh": {
    "defaultMessage": "Back"
  },
  "d5zWyh": {
    "defaultMessage": "Test voice"
  },
  "dOQCL8": {
    "defaultMessage": "Display name"
  },
  "dVD/AR": {
    "defaultMessage": "Top Zappers"
  },
  "dkUMIH": {
    "defaultMessage": "Clip by {name}"
  },
  "e011kf": {
    "defaultMessage": "FAQ",
    "description": "Title: FAQ page"
  },
  "ebmhes": {
    "defaultMessage": "Nostr Extension"
  },
  "f6biFA": {
    "defaultMessage": "Oh, and you have {n} sats of free streaming on us! 💜"
  },
  "fBI91o": {
    "defaultMessage": "Zap"
  },
  "feZ/kG": {
    "defaultMessage": "Login with Private Key (insecure)"
  },
  "g5pX+a": {
    "defaultMessage": "About"
  },
  "gQxxlw": {
    "defaultMessage": "Goal Name"
  },
  "gt65Gg": {
    "defaultMessage": "Stream goals encourage viewers to support streamers via donations."
  },
  "gzsn7k": {
    "defaultMessage": "{n} messages"
  },
  "h6NRY6": {
    "defaultMessage": "No Thanks!"
  },
  "h9mX2/": {
    "defaultMessage": "If you use our in-house zap.stream hosting (cheapest and easiest), copy your stream URL and Stream Key to your OBS settings and you should be good to go."
  },
  "hMzcSq": {
    "defaultMessage": "Messages"
  },
  "heyxZL": {
    "defaultMessage": "Enable text to speech"
  },
  "hpl4BP": {
    "defaultMessage": "Chat Widget"
  },
  "hzSNj4": {
    "defaultMessage": "Dashboard"
  },
  "iKlloU": {
    "defaultMessage": "Suggested Servers"
  },
  "ieGrWo": {
    "defaultMessage": "Follow"
  },
  "ieKb+k": {
    "defaultMessage": "What does it cost to stream?"
  },
  "ipTKP3": {
    "defaultMessage": "Chat Popout"
  },
  "itPgxd": {
    "defaultMessage": "Profile"
  },
  "izWS4J": {
    "defaultMessage": "Unfollow"
  },
  "j/jueq": {
    "defaultMessage": "Raiding {name}"
  },
  "jDDeA0": {
    "defaultMessage": "Your title is very long, please make sure its less than {n} chars."
  },
  "jJLRgo": {
    "defaultMessage": "Publish Clip"
  },
  "jgOqxt": {
    "defaultMessage": "Widgets"
  },
  "jkAQj5": {
    "defaultMessage": "Stream Ended"
  },
  "jr4+vD": {
    "defaultMessage": "Markdown"
  },
  "jvo0vs": {
    "defaultMessage": "Save"
  },
  "k21gTS": {
    "defaultMessage": "e.g. about me"
  },
  "kAEQyV": {
    "defaultMessage": "OK"
  },
  "kGjqZ4": {
    "defaultMessage": "Latest Shorts"
  },
  "kQAf2d": {
    "defaultMessage": "Select"
  },
  "kc5EOy": {
    "defaultMessage": "Username is too long"
  },
  "khJ51Q": {
    "defaultMessage": "Stream Earnings"
  },
  "kp0NPF": {
    "defaultMessage": "Planned"
  },
  "lXbG97": {
    "defaultMessage": "Most Zapped Streamers"
  },
  "lZpRMR": {
    "defaultMessage": "Check here if this stream contains nudity or pornographic content."
  },
  "ljmS5P": {
    "defaultMessage": "Endpoint"
  },
  "miQKuZ": {
    "defaultMessage": "Stream Time"
  },
  "mnJYBQ": {
    "defaultMessage": "Voice"
  },
  "mrwfXX": {
    "defaultMessage": "Shares"
  },
  "msjwph": {
    "defaultMessage": "Keyframe Interval"
  },
  "n19IQE": {
    "defaultMessage": "Recommended size: 1920x1080 (16:9)"
  },
  "n8k1SG": {
    "defaultMessage": "{n}MiB"
  },
  "nBCvvJ": {
    "defaultMessage": "Topup"
  },
  "nOaArs": {
    "defaultMessage": "Setup Profile"
  },
  "nwA8Os": {
    "defaultMessage": "Add card"
  },
  "oHPB8Q": {
    "defaultMessage": "Zap {name}"
  },
  "oZrFyI": {
    "defaultMessage": "Stream type should be HLS"
  },
  "p4N05H": {
    "defaultMessage": "Upload"
  },
  "pOeEMx": {
    "defaultMessage": "Add server"
  },
  "pxF+t0": {
    "defaultMessage": "Popular"
  },
  "q+zTWM": {
    "defaultMessage": "<s>{person}</s> zapped <s>{amount}</s> sats"
  },
  "q9ryv4": {
    "defaultMessage": "Cover image URL (optional)"
  },
  "qx6bv2": {
    "defaultMessage": "Stream Goal (optional)"
  },
  "r2Jjms": {
    "defaultMessage": "Log In"
  },
  "rJqhFR": {
    "defaultMessage": "Stream Setup"
  },
  "rWBFZA": {
    "defaultMessage": "Sexually explicit material ahead!"
  },
  "rgsbu9": {
    "defaultMessage": "Current Viewers"
  },
  "rleUgy": {
    "defaultMessage": "Uploading.."
  },
  "s+ORFl": {
    "defaultMessage": "{m}d {ago}",
    "description": "Number of day(s) relative to now"
  },
  "s5ksS7": {
    "defaultMessage": "Image Link"
  },
  "s7V+5p": {
    "defaultMessage": "Confirm your age"
  },
  "sInm1h": {
    "defaultMessage": "Zap message"
  },
  "sj6WAe": {
    "defaultMessage": "Click the “Stream” button in the top right corner"
  },
  "syEQFE": {
    "defaultMessage": "Publish"
  },
  "tG1ST3": {
    "defaultMessage": "Incoming Zap"
  },
  "tM6fNW": {
    "defaultMessage": "Amazing! Continue.."
  },
  "tNtB9I": {
    "defaultMessage": "Name",
    "description": "Config name column header"
  },
  "tTgdmx": {
    "defaultMessage": "{n,selectordinal,one{@ #st min} two{@ #nd min} few{@ #rd min} other{@ #th min}}"
  },
  "tVCC9m": {
    "defaultMessage": "Sats are small units of Bitcoin. Sending sats on zap.stream is referred to as “zapping” or zaps."
  },
  "thsiMl": {
    "defaultMessage": "terms and conditions"
  },
  "twCRVi": {
    "defaultMessage": "Art"
  },
  "tzMNF3": {
    "defaultMessage": "Status"
  },
  "u6uD94": {
    "defaultMessage": "Create an Account"
  },
  "uYw2LD": {
    "defaultMessage": "Stream"
  },
  "ug01Mk": {
    "defaultMessage": "Time"
  },
  "uksRSi": {
    "defaultMessage": "Latest Videos"
  },
  "vP4dFa": {
    "defaultMessage": "Visit {link} to get some sweet zap.stream merch!"
  },
  "vrTOHJ": {
    "defaultMessage": "{amount} sats"
  },
  "w+2Vw7": {
    "defaultMessage": "Shorts"
  },
  "w0Xm2F": {
    "defaultMessage": "Start typing"
  },
  "w3btjR": {
    "defaultMessage": "Gambling"
  },
  "wCIL7o": {
    "defaultMessage": "Broadcast on Nostr"
  },
  "wCgTu5": {
    "defaultMessage": "Comments"
  },
  "wEQDC6": {
    "defaultMessage": "Edit"
  },
  "wMKVFz": {
    "defaultMessage": "Select voice..."
  },
  "wRGjPp": {
    "defaultMessage": "A nostr extension simply saves your keys so you can safely log in without having to re-enter them every time. ZapStream uses the extension to authorize actions on your behalf without ever seeing your key information. This has a significant advantage over having to trust that websites handle your credentials safely."
  },
  "wTwfnv": {
    "defaultMessage": "Invalid nostr address"
  },
  "we4Lby": {
    "defaultMessage": "Info"
  },
  "x82IOl": {
    "defaultMessage": "Mute"
  },
  "xhQMeQ": {
    "defaultMessage": "Expires"
  },
  "xi3sgh": {
    "defaultMessage": "How do i get more sats?"
  },
  "xmcVZ0": {
    "defaultMessage": "Search"
  },
  "y867Vs": {
    "defaultMessage": "Volume"
  },
  "y8ogtp": {
    "defaultMessage": "{m}w {ago}",
    "description": "Number of week(s) relative to now"
  },
  "yLxIgl": {
    "defaultMessage": "Clips"
  },
  "yR0V+W": {
    "defaultMessage": "To start streaming on zap.stream, follow these steps:"
  },
  "yj8NrY": {
    "defaultMessage": "Clip"
  },
  "yzKwBQ": {
    "defaultMessage": "eg. nsec1xyz"
  },
  "z2qCcJ": {
    "defaultMessage": "Max Video Bitrate"
  },
  "zEYkgY": {
    "defaultMessage": "Talk"
  },
  "zSYDJP": {
    "defaultMessage": "I have my own stream host"
  },
  "zVDHAu": {
    "defaultMessage": "Zap Alert"
  }
}
